prymbr/__init__.py
prymbr/prymbr.py
prymbr-0.0.9.4.dist-info/LICENSE.txt
prymbr-0.0.9.4.dist-info/METADATA
prymbr-0.0.9.4.dist-info/WHEEL
prymbr-0.0.9.4.dist-info/top_level.txt
prymbr-0.0.9.4.dist-info/RECORD
