Metadata-Version: 2.1
Name: prymbr
Version: 0.0.9.4
Summary: A library adding useful and diverse functions such as prime related fuinctions.
Home-page: https://github.com/Vermylion/Prymbr
Author: Guillaume Quarmeau
Author-email: vermylioncode@gmail.com
Project-URL: Bug Tracker, https://github.com/Vermylion/Prymbr
Classifier: Programming Language :: Python :: 3
Classifier: License :: OSI Approved :: MIT License
Classifier: Operating System :: OS Independent
Requires-Python: >=3.6
License-File: LICENSE.txt
